lbs/__init__.py
lbs/client/__init__.py
lbs/client/base.py
lbs/client/amap/__init__.py
lbs/client/amap/api/__init__.py
lbs/client/amap/api/base.py
lbs/client/amap/api/direction.py
lbs/client/amap/api/geocode.py
lbs/client/amap/api/search.py
lbs/client/amap/api/tools.py
lbs/client/amap/api/trafficstatus.py
lbs/client/baidu/__init__.py
lbs/client/qq/__init__.py
lbs/client/qq/api/__init__.py
lbs/client/qq/api/base.py
lbs/client/qq/api/direction.py
lbs/client/qq/api/geocoder.py
lbs/client/qq/api/search.py
lbs/client/qq/api/tools.py
lbs/core/__init__.py
lbs/core/coord_convert.py
lbs/core/exceptions.py
lbs/core/model.py
lbs/core/tile.py
lbs/core/utils.py
lbs-0.2.1.dist-info/LICENSE
lbs-0.2.1.dist-info/METADATA
lbs-0.2.1.dist-info/WHEEL
lbs-0.2.1.dist-info/top_level.txt
lbs-0.2.1.dist-info/RECORD
