Metadata-Version: 2.1
Name: lbs
Version: 0.2.1
Summary: Location Based Services SDK
Home-page: https://github.com/007gzs/lbs
Author: 007gzs
Author-email: 007gzs@sina.com
License: LGPL v3
Keywords: lbs map baidu amap qq autonavi wgs84 gcj02 bd09
Platform: UNKNOWN
Classifier: Development Status :: 3 - Alpha
Classifier: Intended Audience :: Developers
Classifier: Topic :: Software Development :: Build Tools
Classifier: License :: OSI Approved :: GNU Lesser General Public License v3 (LGPLv3)
Classifier: Programming Language :: Python :: 2
Classifier: Programming Language :: Python :: 2.7
Classifier: Programming Language :: Python :: 3
Classifier: Programming Language :: Python :: 3.4
Classifier: Programming Language :: Python :: 3.5
Classifier: Programming Language :: Python :: 3.6
Classifier: Programming Language :: Python :: 3.7
Requires-Dist: six (>=1.8.0)
Requires-Dist: requests (>=2.4.3)
Requires-Dist: optionaldict (>=0.1.0)
